LICENSE
MANIFEST.in
README.md
setup.py
cirrus_run/__init__.py
cirrus_run/api.py
cirrus_run/cli.py
cirrus_run/logging.py
cirrus_run/queries.py
cirrus_run/throbber.py
cirrus_run.egg-info/PKG-INFO
cirrus_run.egg-info/SOURCES.txt
cirrus_run.egg-info/dependency_links.txt
cirrus_run.egg-info/entry_points.txt
cirrus_run.egg-info/requires.txt
cirrus_run.egg-info/top_level.txt
cirrus_run.egg-info/zip-safe