Metadata-Version: 2.1
Name: cirrus-run
Version: 1.0.1
Summary: Command line tool to execute jobs in Cirrus CI
Home-page: https://github.com/sio/cirrus-run
Author: Vitaly Potyarkin
Author-email: sio.wtf@gmail.com
License: Apache-2.0
Download-URL: https://github.com/sio/cirrus-run/archive/v1.0.1.tar.gz
Keywords: api,ci,cirrus-ci
Platform: any
Classifier: Development Status :: 4 - Beta
Classifier: Environment :: Console
Classifier: Intended Audience :: Developers
Classifier: Intended Audience :: System Administrators
Classifier: License :: OSI Approved :: Apache Software License
Classifier: Natural Language :: English
Classifier: Operating System :: OS Independent
Classifier: Programming Language :: Python :: 3
Classifier: Topic :: Software Development :: Quality Assurance
Classifier: Topic :: Software Development
Requires-Python: >=3.4
License-File: LICENSE
